{
  "success": true,
  "data": {
    "hero": {
      "title": "START THE ENGINE AND WE WILL DO THE REST",
      "subtitle": "Optimize industrial performance with cutting-edge technology.",
      "buttonText": "CHECK ON PROJECTS",
      "backgroundImage": "https://res.cloudinary.com/dro6f1fhh/image/upload/v1765479185/construction-cms/file.jpg"
    },
    "features": {
      "title": "We built an environment that you can work easily.",
      "subtitle": "KNOW MORE ABOUT US",
      "linkText": "KNOW MORE ABOUT US →",
      "cards": [
        {
          "title": "Build With Confidence",
          "description": "Our skilled team crafts top-tier, secure designs with state-of-the-art tech. We're committed to meticulous attention from concept to completion, whether it's intricate machinery or a basic device. Rely on our expertise for dependable project execution, ensuring your trust in our capable hands.",
          "_id": "692f1ae338cdd6b107e5f7f0"
        },
        {
          "title": "Total Transparency",
          "description": "Transparency is key for trust in collaborations. We prioritize clear communication, offering updates and sharing challenges. We welcome feedback, fostering open dialogue to enhance mutual understanding and achieve our goals with clients and colleagues.",
          "_id": "692f1ae338cdd6b107e5f7f1"
        },
        {
          "title": "Detailed Projects",
          "description": "We've recently completed thrilling projects and seek more opportunities. Proud of our work, we're eager for new ventures. If you require expertise, reach out for project discussions. We're ready to assist and explore how we can contribute to your needs.",
          "_id": "692f1ae338cdd6b107e5f7f2"
        }
      ]
    },
    "companyInfo": {
      "logo": "/logo.jpeg",
      "brandName": "KUNAL™",
      "companyName": "Kunal Global Fabtech Pvt. Ltd.",
      "description": "KGFPL, led by Mr. Sanjay Singh & Mr. Mahendra Singh, excels in technical and financial administration. We have specialization in mechanical installation and commissioning for the various refinery and power projects to the development of a new India.",
      "buttonText": "ABOUT US",
      "image": "https://res.cloudinary.com/dro6f1fhh/image/upload/v1766037567/construction-cms/file.jpg",
      "badgeValue": "15",
      "badgeLabel": ""
    },
    "cta": {
      "title": "So, What are You Waiting For? Let's Talk About Your Project!",
      "description": "Get in touch with us, share your aspirations, and watch as together we craft a journey where your dreams truly take flight.",
      "buttonText": "START YOUR PROJECT"
    },
    "_id": "692ed91392c4cc43f1a4fe0d",
    "clientLogos": [
      {
        "image": "/image3.png",
        "alt": "Company Logo 1",
        "_id": "692f1ae338cdd6b107e5f7e8"
      },
      {
        "image": "/image4.png",
        "alt": "Company Logo 2",
        "_id": "692f1ae338cdd6b107e5f7e9"
      },
      {
        "image": "/image5.png",
        "alt": "Company Logo 3",
        "_id": "692f1ae338cdd6b107e5f7ea"
      },
      {
        "image": "/image6.png",
        "alt": "Company Logo 4",
        "_id": "692f1ae338cdd6b107e5f7eb"
      },
      {
        "image": "/image7.png",
        "alt": "Company Logo 5",
        "_id": "692f1ae338cdd6b107e5f7ec"
      }
    ],
    "stats": [
      {
        "value": "100%",
        "label": "Satisfied Clients",
        "_id": "692f1ae338cdd6b107e5f7ed"
      },
      {
        "value": "2000+",
        "label": "Workforce on projects",
        "_id": "692f1ae338cdd6b107e5f7ee"
      },
      {
        "value": "70+",
        "label": "Projects Completed",
        "_id": "692f1ae338cdd6b107e5f7ef"
      }
    ],
    "updatedAt": "2025-12-18T05:59:31.638Z",
    "createdAt": "2025-12-02T12:18:27.055Z",
    "__v": 24
  }
}